Metadata-Version: 2.4
Name: iflow-mcp_mcp-paperswithcode
Version: 0.1.0
Summary: Add your description here
Requires-Python: >=3.10
License-File: LICENSE
Requires-Dist: mcp[cli]>=1.4.1
Requires-Dist: pypdf2>=3.0.1
Requires-Dist: requests>=2.32.3
Dynamic: license-file
